JsonRpcExtended.py
LICENSE.txt
MANIFEST.in
README.md
protocols.txt
pyproject.toml
setup.cfg
setup.py
JsonRpcExtended.egg-info/PKG-INFO
JsonRpcExtended.egg-info/SOURCES.txt
JsonRpcExtended.egg-info/dependency_links.txt
JsonRpcExtended.egg-info/entry_points.txt
JsonRpcExtended.egg-info/top_level.txt